README.md
setup.py
kfmd/__init__.py
kfmd/metadata.py
kfmd.egg-info/PKG-INFO
kfmd.egg-info/SOURCES.txt
kfmd.egg-info/dependency_links.txt
kfmd.egg-info/top_level.txt
kfmd/openapi_client/__init__.py
kfmd/openapi_client/api_client.py
kfmd/openapi_client/configuration.py
kfmd/openapi_client/exceptions.py
kfmd/openapi_client/rest.py
kfmd/openapi_client/api/__init__.py
kfmd/openapi_client/api/metadata_service_api.py
kfmd/openapi_client/models/__init__.py
kfmd/openapi_client/models/api_create_artifact_response.py
kfmd/openapi_client/models/api_create_artifact_type_response.py
kfmd/openapi_client/models/api_create_execution_response.py
kfmd/openapi_client/models/api_create_execution_type_response.py
kfmd/openapi_client/models/api_get_artifact_response.py
kfmd/openapi_client/models/api_get_artifact_type_response.py
kfmd/openapi_client/models/api_get_execution_response.py
kfmd/openapi_client/models/api_get_execution_type_response.py
kfmd/openapi_client/models/api_list_artifact_types_response.py
kfmd/openapi_client/models/api_list_artifacts_response.py
kfmd/openapi_client/models/api_list_events_response.py
kfmd/openapi_client/models/api_list_execution_types_response.py
kfmd/openapi_client/models/api_list_executions_response.py
kfmd/openapi_client/models/event_path.py
kfmd/openapi_client/models/ml_metadata_artifact.py
kfmd/openapi_client/models/ml_metadata_artifact_struct_type.py
kfmd/openapi_client/models/ml_metadata_artifact_type.py
kfmd/openapi_client/models/ml_metadata_dict_artifact_struct_type.py
kfmd/openapi_client/models/ml_metadata_event.py
kfmd/openapi_client/models/ml_metadata_event_type.py
kfmd/openapi_client/models/ml_metadata_execution.py
kfmd/openapi_client/models/ml_metadata_execution_state.py
kfmd/openapi_client/models/ml_metadata_execution_type.py
kfmd/openapi_client/models/ml_metadata_intersection_artifact_struct_type.py
kfmd/openapi_client/models/ml_metadata_list_artifact_struct_type.py
kfmd/openapi_client/models/ml_metadata_property_type.py
kfmd/openapi_client/models/ml_metadata_tuple_artifact_struct_type.py
